datalad_core/__init__.py
datalad_core/_version.py
datalad_core/py.typed
datalad_core/commands/__init__.py
datalad_core/commands/dataset.py
datalad_core/commands/decorator.py
datalad_core/commands/default_result_handler.py
datalad_core/commands/exceptions.py
datalad_core/commands/param_constraint.py
datalad_core/commands/preproc.py
datalad_core/commands/result_handler.py
datalad_core/commands/tests/__init__.py
datalad_core/commands/tests/test_cmd.py
datalad_core/commands/tests/test_dataset.py
datalad_core/commands/tests/test_preproc.py
datalad_core/config/__init__.py
datalad_core/config/defaults.py
datalad_core/config/git.py
datalad_core/config/gitenv.py
datalad_core/config/item.py
datalad_core/config/manager.py
datalad_core/config/utils.py
datalad_core/config/tests/__init__.py
datalad_core/config/tests/test_defaults.py
datalad_core/config/tests/test_git.py
datalad_core/config/tests/test_gitenv.py
datalad_core/config/tests/test_manager.py
datalad_core/config/tests/test_utils.py
datalad_core/constraints/__init__.py
datalad_core/constraints/basic.py
datalad_core/constraints/constraint.py
datalad_core/constraints/exceptions.py
datalad_core/constraints/path.py
datalad_core/constraints/wrapper.py
datalad_core/constraints/tests/__init__.py
datalad_core/constraints/tests/test_basic.py
datalad_core/constraints/tests/test_constraint.py
datalad_core/constraints/tests/test_exceptions.py
datalad_core/constraints/tests/test_path.py
datalad_core/constraints/tests/test_wrapper.py
datalad_core/consts/__init__.py
datalad_core/repo/__init__.py
datalad_core/repo/annex.py
datalad_core/repo/flyweight.py
datalad_core/repo/gitmanaged.py
datalad_core/repo/repo.py
datalad_core/repo/utils.py
datalad_core/repo/worktree.py
datalad_core/repo/tests/__init__.py
datalad_core/repo/tests/test_annex.py
datalad_core/repo/tests/test_repo.py
datalad_core/repo/tests/test_worktree.py
datalad_core/runners/__init__.py
datalad_core/runners/annex.py
datalad_core/runners/git.py
datalad_core/runners/imports.py
datalad_core-0.1.2.dist-info/METADATA
datalad_core-0.1.2.dist-info/WHEEL
datalad_core-0.1.2.dist-info/licenses/LICENSE
datalad_core-0.1.2.dist-info/RECORD
