Metadata-Version: 2.4
Name: datalad-core
Version: 0.1.2
Summary: core library for the datalad-framework
Project-URL: Homepage, https://github.com/datalad/datalad-core
Project-URL: Documentation, https://github.com/datalad/datalad-core#readme
Project-URL: Issues, https://github.com/datalad/datalad-core/issues
Project-URL: Source, https://github.com/datalad/datalad-core
Project-URL: Changelog, https://github.com/datalad/datalad-core/blob/main/CHANGELOG.md
Author-email: Michael Hanke <michael.hanke@gmail.com>
Maintainer-email: Michael Hanke <michael.hanke@gmail.com>
License-Expression: MIT
License-File: LICENSE
Keywords: datalad,git,git-annex
Classifier: Development Status :: 3 - Alpha
Classifier: Intended Audience :: Developers
Classifier: Intended Audience :: End Users/Desktop
Classifier: License :: OSI Approved :: MIT License
Classifier: Natural Language :: English
Classifier: Operating System :: OS Independent
Classifier: Programming Language :: Python
Classifier: Programming Language :: Python :: 3
Classifier: Programming Language :: Python :: 3.10
Classifier: Programming Language :: Python :: 3.11
Classifier: Programming Language :: Python :: 3.12
Classifier: Programming Language :: Python :: 3.13
Classifier: Programming Language :: Python :: Implementation :: CPython
Classifier: Programming Language :: Python :: Implementation :: PyPy
Classifier: Topic :: Software Development
Classifier: Topic :: Software Development :: Version Control
Classifier: Topic :: Software Development :: Version Control :: Git
Requires-Python: >=3.10
Requires-Dist: datasalad>=0.4.0
Requires-Dist: git-annex>=10.20250721
Provides-Extra: docs
Requires-Dist: sphinx; extra == 'docs'
Requires-Dist: sphinx-rtd-theme; extra == 'docs'
